decode_server_flask.py
decode_server_flask-1.0.0.dist-info/LICENSE.txt
decode_server_flask-1.0.0.dist-info/METADATA
decode_server_flask-1.0.0.dist-info/WHEEL
decode_server_flask-1.0.0.dist-info/top_level.txt
decode_server_flask-1.0.0.dist-info/RECORD
