Metadata-Version: 2.1
Name: decode-server-flask
Version: 1.0.0
Summary: Flask middleware for Decode Auth
Home-page: https://github.com/usedecode/decode_server
Author: Davor Badrov
Author-email: flask@decodeauth.com
License: UNKNOWN
Platform: UNKNOWN
Classifier: Programming Language :: Python :: 3
Classifier: Programming Language :: Python :: 3.6
Classifier: Programming Language :: Python :: 3.7
Classifier: Programming Language :: Python :: 3.8
Classifier: Programming Language :: Python :: 3.9
Classifier: License :: OSI Approved :: MIT License
Classifier: Operating System :: OS Independent
Requires-Dist: flask (~=1.1)
Requires-Dist: python-jose (~=3.2)
Provides-Extra: dev
Requires-Dist: pytest (>=3.7) ; extra == 'dev'
Requires-Dist: twine (>=3.2) ; extra == 'dev'
